root_directory/__init__.py
root_directory-0.1.4.dist-info/LICENSE
root_directory-0.1.4.dist-info/METADATA
root_directory-0.1.4.dist-info/WHEEL
root_directory-0.1.4.dist-info/top_level.txt
root_directory-0.1.4.dist-info/RECORD
