Metadata-Version: 2.1
Name: root-directory
Version: 0.1.4
Summary: A no-nonsense utility for importing relative to root
Author-email: Kristjan Kongas <kongaskristjan@gmail.com>
License: This is free and unencumbered software released into the public domain.        
Project-URL: Homepage, https://github.com/kongaskristjan/root_directory
Project-URL: Bug Tracker, https://github.com/kongaskristjan/root_directory/issues
Classifier: Programming Language :: Python :: 3
Classifier: License :: OSI Approved :: The Unlicense (Unlicense)
Classifier: Operating System :: OS Independent
Requires-Python: >=3.5
License-File: LICENSE
